pygrowup/__init__.py
pygrowup/exceptions.py
pygrowup/pygrowup.py
pygrowup/tests.py
pygrowup/tables/__init__.py
pygrowup/tables/by_day/__init__.py
pygrowup/tables/by_day/acfa.py
pygrowup/tables/by_day/bmifa.py
pygrowup/tables/by_day/hcfa.py
pygrowup/tables/by_day/lfa.py
pygrowup/tables/by_day/ssfa.py
pygrowup/tables/by_day/tsfa.py
pygrowup/tables/by_day/wfa.py
pygrowup/tables/by_day/wfh.py
pygrowup/tables/by_day/wfl.py
pygrowup/tables/by_month/__init__.py
pygrowup/tables/by_month/acfa.py
pygrowup/tables/by_month/bmifa.py
pygrowup/tables/by_month/lfa.py
pygrowup/tables/by_month/wfa.py
pygrowup/test_datasets/MySurvey_z_st.csv
pygrowup/test_datasets/test_dataset.csv
pygrowup2-1.0.0.dist-info/METADATA
pygrowup2-1.0.0.dist-info/WHEEL
pygrowup2-1.0.0.dist-info/licenses/LICENSE
pygrowup2-1.0.0.dist-info/RECORD
