Metadata-Version: 2.4
Name: pygrowup2
Version: 1.0.0
Summary: Calculate z-scores of anthropometric measurements based on WHO child growth standards
Project-URL: Homepage, https://github.com/jbaldivieso/pygrowup2
Project-URL: Repository, https://github.com/jbaldivieso/pygrowup2
Project-URL: Issues, https://github.com/jbaldivieso/pygrowup2/issues
Author-email: Jon Baldivieso <jbaldivieso@gmail.com>
License-Expression: BSD-3-Clause
License-File: LICENSE
Keywords: MUAC,WHO,anthropometry,child growth,nutrition,z-score
Classifier: Development Status :: 5 - Production/Stable
Classifier: Intended Audience :: Developers
Classifier: Intended Audience :: Healthcare Industry
Classifier: Intended Audience :: Science/Research
Classifier: License :: OSI Approved :: BSD License
Classifier: Operating System :: OS Independent
Classifier: Programming Language :: Python :: 3
Classifier: Programming Language :: Python :: 3.10
Classifier: Programming Language :: Python :: 3.11
Classifier: Programming Language :: Python :: 3.12
Classifier: Programming Language :: Python :: 3.13
Classifier: Topic :: Scientific/Engineering :: Bio-Informatics
Classifier: Topic :: Scientific/Engineering :: Medical Science Apps.
Requires-Python: >=3.10
